Metadata-Version: 2.1
Name: clear-formatting
Version: 0.9.3
Summary: A module providing a facade for clear formatting values into strings.
Home-page: https://github.com/MitryP/clear-formatting
Author: Dmytro Popov
Author-email: thedmitryp@ukr.net
License: Apache-2.0
Download-URL: https://github.com/mitryp/clear-formatting/archive/refs/tags/0.9.3.tar.gz
Keywords: formatting,string,number,simplify,value-formatting,format,formatter,facade,open-source,string formatting
Platform: UNKNOWN
Classifier: Development Status :: 4 - Beta
Classifier: Intended Audience :: Developers
Classifier: Topic :: Software Development :: Libraries :: Python Modules
Classifier: Topic :: Software Development :: Libraries
Classifier: License :: OSI Approved :: Apache Software License
Classifier: Operating System :: OS Independent
Classifier: Programming Language :: Python :: 3
Classifier: Programming Language :: Python :: 3.6
Classifier: Programming Language :: Python :: 3.7
Classifier: Programming Language :: Python :: 3.8
Classifier: Programming Language :: Python :: 3.9
Classifier: Programming Language :: Python :: 3.10
License-File: LICENSE
